vlogging/__init__.py
vlogging/formatters.py
vlogging/handlers.py
vlogging/loggers.py
vlogging-0.0.3.dist-info/LICENSE
vlogging-0.0.3.dist-info/METADATA
vlogging-0.0.3.dist-info/WHEEL
vlogging-0.0.3.dist-info/top_level.txt
vlogging-0.0.3.dist-info/RECORD
