Metadata-Version: 2.1
Name: vlogging
Version: 0.0.3
Summary: Easy to use logger.
Author-email: Yuya Honda <yuyahnd.info@gmail.com>
Maintainer-email: Yuya Honda <yuyahnd.info@gmail.com>
License: MIT License
Project-URL: Homepage, https://github.com/yuyahnd/vlogging
Project-URL: Bug Tracker, https://github.com/yuyahnd/vlogging/issues
Project-URL: Repository, https://github.com/yuyahnd/vlogging.git
Keywords: vlogging,logging,logger,log
Classifier: Programming Language :: Python :: 3
Classifier: Programming Language :: Python :: 3.7
Classifier: Programming Language :: Python :: 3.8
Classifier: Programming Language :: Python :: 3.9
Classifier: Programming Language :: Python :: 3.10
Classifier: Programming Language :: Python :: 3.11
Classifier: License :: OSI Approved :: MIT License
Requires-Python: >=3.7
License-File: LICENSE
Provides-Extra: dev
Requires-Dist: pytest (==7.2.1) ; extra == 'dev'
Requires-Dist: tox (==4.4.4) ; extra == 'dev'
